[
  {
    "_id": "1",
    "owner": "1",
    "name": "Boston Commons Retreat",
    "type": "Apartment",
    "description": "This is a beautiful apartment located near the commons. It is a 2 bedroom apartment with a full kitchen and bathroom. It is available for weekly or monthly rentals.",
    "location": {
      "street": "120 Tremont Street",
      "city": "Boston",
      "state": "MA",
      "zipcode": "02108"
    },
    "beds": 2,
    "baths": 1,
    "square_feet": 1500,
    "amenities": [
      "Wifi",
      "Full kitchen",
      "Washer & Dryer",
      "Free Parking",
      "Hot Tub",
      "24/7 Security",
      "Wheelchair Accessible",
      "Elevator Access",
      "Dishwasher",
      "Gym/Fitness Center",
      "Air Conditioning",
      "Balcony/Patio",
      "Smart TV",
      "Coffee Maker"
    ],
    "rates": {
      "weekly": 1100,
      "monthly": 4200
    },
    "seller_info": {
      "name": "John Doe",
      "email": "john@gmail.com",
      "phone": "617-555-5555"
    },
    "isFeatured": false,
    "createdAt": "2024-01-01T00:00:00.000Z",
    "updatedAt": "2024-01-01T00:00:00.000Z"
  },
  {
    "_id": "2",
    "owner": "1",
    "name": "Cozy Downtown Loft",
    "type": "Apartment",
    "description": "A cozy downtown loft with great city views.",
    "location": {
      "street": "45 Main Street",
      "city": "New York",
      "state": "NY",
      "zipcode": "10001"
    },
    "beds": 1,
    "baths": 1,
    "square_feet": 1800,
    "amenities": [
      "Wifi",
      "Full kitchen",
      "Washer & Dryer",
      "Free Parking",
      "Hot Tub",
      "24/7 Security",
      "Wheelchair Accessible",
      "Elevator Access",
      "Dishwasher",
      "High-Speed Internet",
      "Air Conditioning",
      "Smart TV",
      "Outdoor Grill/BBQ"
    ],
    "rates": {
      "weekly": 1000,
      "monthly": 4000
    },
    "seller_info": {
      "name": "Jane Smith",
      "email": "jane@gmail.com",
      "phone": "212-555-5555"
    },
    "images": ["b1.jpg", "b2.jpg", "b3.jpg"],
    "isFeatured": false,
    "createdAt": "2024-01-02T00:00:00.000Z",
    "updatedAt": "2024-01-02T00:00:00.000Z"
  },
  {
    "_id": "3",
    "owner": "2",
    "name": "Luxury Condo with a View",
    "type": "Condo",
    "description": "Experience luxury in this stunning condo with breathtaking views.",
    "location": {
      "street": "500 Lux Lane",
      "city": "Los Angeles",
      "state": "CA",
      "zipcode": "90001"
    },
    "beds": 3,
    "baths": 2,
    "square_feet": 2200,
    "amenities": [
      "Wifi",
      "Full kitchen",
      "Washer & Dryer",
      "Free Parking",
      "Hot Tub",
      "24/7 Security",
      "Wheelchair Accessible",
      "Elevator Access",
      "Dishwasher",
      "Swimming Pool",
      "Gym/Fitness Center",
      "Air Conditioning",
      "Smart TV",
      "Coffee Maker"
    ],
    "rates": {
      "nightly": 200,
      "weekly": 750,
      "monthly": 3300
    },
    "seller_info": {
      "name": "David Johnson",
      "email": "david@gmail.com",
      "phone": "213-555-5555"
    },
    "images": ["c1.jpg", "c2.jpg", "c3.jpg"],
    "isFeatured": false,
    "createdAt": "2024-01-03T00:00:00.000Z",
    "updatedAt": "2024-01-03T00:00:00.000Z"
  },
  {
    "_id": "4",
    "owner": "2",
    "name": "Charming Cottage Getaway",
    "type": "Cottage Or Cabin",
    "description": "Escape to this charming cottage for a peaceful retreat.",
    "location": {
      "street": "123 Countryside Lane",
      "city": "Austin",
      "state": "TX",
      "zipcode": "78701"
    },
    "beds": 1,
    "baths": 1,
    "square_feet": 900,
    "amenities": [
      "Fireplace",
      "Outdoor Grill/BBQ",
      "Balcony/Patio",
      "Coffee Maker"
    ],
    "rates": {
      "weekly": 2000
    },
    "seller_info": {
      "name": "Emily Davis",
      "email": "emily@gmail.com",
      "phone": "512-555-5555"
    },
    "images": ["d1.jpg", "d2.jpg", "d3.jpg"],
    "isFeatured": false,
    "createdAt": "2024-01-04T00:00:00.000Z",
    "updatedAt": "2024-01-04T00:00:00.000Z"
  }
]
